subhikshaImputeX/__init__.py
subhikshaImputeX/core.py
subhikshaImputeX/detector.py
subhikshaImputeX/evaluator.py
subhikshaImputeX/strategies.py
subhikshaImputeX/utils.py
subhikshaimputex-0.1.0.dist-info/licenses/LICENSE
tests/__init__.py
tests/test_imputer.py
tests/test_strategies.py
subhikshaimputex-0.1.0.dist-info/METADATA
subhikshaimputex-0.1.0.dist-info/WHEEL
subhikshaimputex-0.1.0.dist-info/top_level.txt
subhikshaimputex-0.1.0.dist-info/RECORD
